<?xml version="1.0" ?>
<SetObject>
  <ChangeMode_3DtoForward>
    <Collision_Height>30</Collision_Height>
    <Collision_Width>10</Collision_Width>
    <GroundOffset>0</GroundOffset>
    <TargetDirection>
      <x>-206.457</x>
      <y>-46.349</y>
      <z>-718.56</z>
    </TargetDirection>
    <Template>0</Template>
    <m_CurveCorrectionForce>1</m_CurveCorrectionForce>
    <m_DashPathSideMoveRate>0.6</m_DashPathSideMoveRate>
    <m_IsChangeCamera>true</m_IsChangeCamera>
    <m_IsEnableFromBack>true</m_IsEnableFromBack>
    <m_IsEnableFromFront>true</m_IsEnableFromFront>
    <m_IsLimitEdge>false</m_IsLimitEdge>
    <m_IsReverseCameraEnable>false</m_IsReverseCameraEnable>
    <m_PathCorrectionForce>0</m_PathCorrectionForce>
    <IsCastShadow>true</IsCastShadow>
    <Range>100</Range>
    <Position>
      <x>-206.392</x>
      <y>-37.4177</y>
      <z>-715.164</z>
    </Position>
    <Rotation>
      <x>0</x>
      <y>1</y>
      <z>0</z>
      <w>0</w>
    </Rotation>
    <SetObjectID>2223</SetObjectID>
  </ChangeMode_3DtoForward>
  <ObjCameraPathTarget>
    <Ease_Time_Enter>0</Ease_Time_Enter>
    <Ease_Time_Leave>0</Ease_Time_Leave>
    <EyePathType>0</EyePathType>
    <EyeSpeed>5</EyeSpeed>
    <Fovy>45</Fovy>
    <GroundOffset>0</GroundOffset>
    <IsCameraView>false</IsCameraView>
    <IsCollision>true</IsCollision>
    <IsControllable>false</IsControllable>
    <OffsetOnEyePath>-15</OffsetOnEyePath>
    <PanAndTangentBlend>0</PanAndTangentBlend>
    <PathID>0</PathID>
    <Target>
      <SetObjectID>0</SetObjectID>
    </Target>
    <TargetOffset_Front>0</TargetOffset_Front>
    <TargetOffset_Right>0</TargetOffset_Right>
    <TargetOffset_Up>0</TargetOffset_Up>
    <TargetPositionFix>
      <x>0</x>
      <y>0</y>
      <z>0</z>
    </TargetPositionFix>
    <Target_Type>0</Target_Type>
    <ZRot>0</ZRot>
    <Position>
      <x>-206.021</x>
      <y>-77.3426</y>
      <z>-1280.53</z>
    </Position>
    <Rotation>
      <x>0</x>
      <y>-0.000286728</y>
      <z>0</z>
      <w>-1</w>
    </Rotation>
    <SetObjectID>2225</SetObjectID>
  </ObjCameraPathTarget>
  <ChangeVolumeCamera>
    <Collision_Height>44</Collision_Height>
    <Collision_Length>160</Collision_Length>
    <Collision_Width>48</Collision_Width>
    <DefaultStatus>0</DefaultStatus>
    <Ease_Time_Enter>0.5</Ease_Time_Enter>
    <Ease_Time_Leave>0.5</Ease_Time_Leave>
    <GroundOffset>0</GroundOffset>
    <IsCameraView>false</IsCameraView>
    <IsEnableCollision>false</IsEnableCollision>
    <LineType>0</LineType>
    <PositionList />
    <Priority>0</Priority>
    <Shape_Type>0</Shape_Type>
    <Target>
      <SetObjectID>2225</SetObjectID>
    </Target>
    <IsCastShadow>true</IsCastShadow>
    <Range>100</Range>
    <Position>
      <x>-200.631</x>
      <y>-72.1445</y>
      <z>-1372.99</z>
    </Position>
    <Rotation>
      <x>0</x>
      <y>-1</y>
      <z>0</z>
      <w>0.000286893</w>
    </Rotation>
    <SetObjectID>2226</SetObjectID>
  </ChangeVolumeCamera>
  <ChangeVolumeCamera>
    <Collision_Height>38</Collision_Height>
    <Collision_Length>27</Collision_Length>
    <Collision_Width>45</Collision_Width>
    <DefaultStatus>0</DefaultStatus>
    <Ease_Time_Enter>0</Ease_Time_Enter>
    <Ease_Time_Leave>0</Ease_Time_Leave>
    <GroundOffset>0</GroundOffset>
    <IsCameraView>false</IsCameraView>
    <IsEnableCollision>false</IsEnableCollision>
    <LineType>0</LineType>
    <PositionList />
    <Priority>2</Priority>
    <Shape_Type>0</Shape_Type>
    <Target>
      <SetObjectID>2366</SetObjectID>
    </Target>
    <IsCastShadow>true</IsCastShadow>
    <Range>100</Range>
    <Position>
      <x>11.8627</x>
      <y>-56.4136</y>
      <z>-349.743</z>
    </Position>
    <Rotation>
      <x>0.00943337</x>
      <y>0</y>
      <z>0.000669507</z>
      <w>0.999955</w>
    </Rotation>
    <SetObjectID>2252</SetObjectID>
  </ChangeVolumeCamera>
  <ChangeVolumeCamera>
    <Collision_Height>190</Collision_Height>
    <Collision_Length>88</Collision_Length>
    <Collision_Width>63</Collision_Width>
    <DefaultStatus>0</DefaultStatus>
    <Ease_Time_Enter>1.5</Ease_Time_Enter>
    <Ease_Time_Leave>1.5</Ease_Time_Leave>
    <GroundOffset>0</GroundOffset>
    <IsCameraView>false</IsCameraView>
    <IsEnableCollision>false</IsEnableCollision>
    <LineType>0</LineType>
    <PositionList />
    <Priority>0</Priority>
    <Shape_Type>0</Shape_Type>
    <Target>
      <SetObjectID>2268</SetObjectID>
    </Target>
    <IsCastShadow>true</IsCastShadow>
    <Range>100</Range>
    <Position>
      <x>18.3289</x>
      <y>10.8413</y>
      <z>-293.751</z>
    </Position>
    <Rotation>
      <x>0</x>
      <y>0</y>
      <z>0</z>
      <w>1</w>
    </Rotation>
    <SetObjectID>2267</SetObjectID>
  </ChangeVolumeCamera>
  <ObjCameraParallel>
    <Distance>5</Distance>
    <Ease_Time_Enter>0</Ease_Time_Enter>
    <Ease_Time_Leave>0</Ease_Time_Leave>
    <Fovy>45</Fovy>
    <GroundOffset>0</GroundOffset>
    <IsCameraView>false</IsCameraView>
    <IsCollision>true</IsCollision>
    <IsControllable>false</IsControllable>
    <OffsetPitch>0</OffsetPitch>
    <OffsetYaw>0</OffsetYaw>
    <Pitch>40</Pitch>
    <Target>
      <SetObjectID>0</SetObjectID>
    </Target>
    <TargetOffset_Front>0</TargetOffset_Front>
    <TargetOffset_Right>0</TargetOffset_Right>
    <TargetOffset_Up>0</TargetOffset_Up>
    <TargetPositionFix>
      <x>0</x>
      <y>0</y>
      <z>0</z>
    </TargetPositionFix>
    <Target_Type>0</Target_Type>
    <Yaw>0</Yaw>
    <ZRot>0</ZRot>
    <IsCastShadow>true</IsCastShadow>
    <Range>100000</Range>
    <Position>
      <x>14.2754</x>
      <y>-29.7902</y>
      <z>-309.278</z>
    </Position>
    <Rotation>
      <x>0</x>
      <y>0</y>
      <z>0</z>
      <w>1</w>
    </Rotation>
    <SetObjectID>2268</SetObjectID>
  </ObjCameraParallel>
  <ChangeVolumeCamera>
    <Collision_Height>40</Collision_Height>
    <Collision_Length>28</Collision_Length>
    <Collision_Width>42</Collision_Width>
    <DefaultStatus>0</DefaultStatus>
    <Ease_Time_Enter>2.5</Ease_Time_Enter>
    <Ease_Time_Leave>1</Ease_Time_Leave>
    <GroundOffset>0</GroundOffset>
    <IsCameraView>false</IsCameraView>
    <IsEnableCollision>false</IsEnableCollision>
    <LineType>0</LineType>
    <PositionList />
    <Priority>0</Priority>
    <Shape_Type>0</Shape_Type>
    <Target>
      <SetObjectID>2270</SetObjectID>
    </Target>
    <IsCastShadow>true</IsCastShadow>
    <Range>100</Range>
    <Position>
      <x>22.6519</x>
      <y>-50.7797</y>
      <z>-669.719</z>
    </Position>
    <Rotation>
      <x>0</x>
      <y>0</y>
      <z>0</z>
      <w>1</w>
    </Rotation>
    <SetObjectID>2269</SetObjectID>
  </ChangeVolumeCamera>
  <ObjCameraParallel>
    <Distance>5</Distance>
    <Ease_Time_Enter>0</Ease_Time_Enter>
    <Ease_Time_Leave>0</Ease_Time_Leave>
    <Fovy>45</Fovy>
    <GroundOffset>0</GroundOffset>
    <IsCameraView>false</IsCameraView>
    <IsCollision>true</IsCollision>
    <IsControllable>true</IsControllable>
    <OffsetPitch>0</OffsetPitch>
    <OffsetYaw>0</OffsetYaw>
    <Pitch>0</Pitch>
    <Target>
      <SetObjectID>0</SetObjectID>
    </Target>
    <TargetOffset_Front>0</TargetOffset_Front>
    <TargetOffset_Right>0</TargetOffset_Right>
    <TargetOffset_Up>0</TargetOffset_Up>
    <TargetPositionFix>
      <x>0</x>
      <y>0</y>
      <z>0</z>
    </TargetPositionFix>
    <Target_Type>0</Target_Type>
    <Yaw>95</Yaw>
    <ZRot>0</ZRot>
    <IsCastShadow>true</IsCastShadow>
    <Range>100000</Range>
    <Position>
      <x>21.2328</x>
      <y>-56.5806</y>
      <z>-671.74</z>
    </Position>
    <Rotation>
      <x>0</x>
      <y>0</y>
      <z>0</z>
      <w>1</w>
    </Rotation>
    <SetObjectID>2270</SetObjectID>
  </ObjCameraParallel>
  <ChangeVolumeCamera>
    <Collision_Height>40</Collision_Height>
    <Collision_Length>55</Collision_Length>
    <Collision_Width>161</Collision_Width>
    <DefaultStatus>0</DefaultStatus>
    <Ease_Time_Enter>1</Ease_Time_Enter>
    <Ease_Time_Leave>1</Ease_Time_Leave>
    <GroundOffset>0</GroundOffset>
    <IsCameraView>false</IsCameraView>
    <IsEnableCollision>false</IsEnableCollision>
    <LineType>0</LineType>
    <PositionList />
    <Priority>0</Priority>
    <Shape_Type>0</Shape_Type>
    <Target>
      <SetObjectID>2386</SetObjectID>
    </Target>
    <IsCastShadow>true</IsCastShadow>
    <Range>100</Range>
    <Position>
      <x>-104.687</x>
      <y>-47.7218</y>
      <z>-671.537</z>
    </Position>
    <Rotation>
      <x>0</x>
      <y>0</y>
      <z>0</z>
      <w>1</w>
    </Rotation>
    <SetObjectID>2276</SetObjectID>
  </ChangeVolumeCamera>
  <ChangeVolumeCamera>
    <Collision_Height>14</Collision_Height>
    <Collision_Length>35</Collision_Length>
    <Collision_Width>45</Collision_Width>
    <DefaultStatus>0</DefaultStatus>
    <Ease_Time_Enter>2</Ease_Time_Enter>
    <Ease_Time_Leave>1</Ease_Time_Leave>
    <GroundOffset>0</GroundOffset>
    <IsCameraView>false</IsCameraView>
    <IsEnableCollision>false</IsEnableCollision>
    <LineType>0</LineType>
    <PositionList />
    <Priority>0</Priority>
    <Shape_Type>0</Shape_Type>
    <Target>
      <SetObjectID>2286</SetObjectID>
    </Target>
    <IsCastShadow>true</IsCastShadow>
    <Range>100</Range>
    <Position>
      <x>-21.1554</x>
      <y>-64.7617</y>
      <z>-669.303</z>
    </Position>
    <Rotation>
      <x>0</x>
      <y>0</y>
      <z>0</z>
      <w>1</w>
    </Rotation>
    <SetObjectID>2285</SetObjectID>
  </ChangeVolumeCamera>
  <ObjCameraParallel>
    <Distance>7</Distance>
    <Ease_Time_Enter>0</Ease_Time_Enter>
    <Ease_Time_Leave>0</Ease_Time_Leave>
    <Fovy>45</Fovy>
    <GroundOffset>0</GroundOffset>
    <IsCameraView>false</IsCameraView>
    <IsCollision>true</IsCollision>
    <IsControllable>true</IsControllable>
    <OffsetPitch>0</OffsetPitch>
    <OffsetYaw>0</OffsetYaw>
    <Pitch>10</Pitch>
    <Target>
      <SetObjectID>0</SetObjectID>
    </Target>
    <TargetOffset_Front>0</TargetOffset_Front>
    <TargetOffset_Right>0</TargetOffset_Right>
    <TargetOffset_Up>0</TargetOffset_Up>
    <TargetPositionFix>
      <x>0</x>
      <y>0</y>
      <z>0</z>
    </TargetPositionFix>
    <Target_Type>0</Target_Type>
    <Yaw>-60</Yaw>
    <ZRot>0</ZRot>
    <IsCastShadow>true</IsCastShadow>
    <Range>100000</Range>
    <Position>
      <x>-16.9082</x>
      <y>-62.3697</y>
      <z>-669.197</z>
    </Position>
    <Rotation>
      <x>0</x>
      <y>0</y>
      <z>0</z>
      <w>1</w>
    </Rotation>
    <SetObjectID>2286</SetObjectID>
  </ObjCameraParallel>
  <Spring>
    <DebugShotTimeLength>2</DebugShotTimeLength>
    <FirstSpeed>29.6</FirstSpeed>
    <GroundOffset>0</GroundOffset>
    <HasBase>false</HasBase>
    <IsChangeCameraWhenPathChange>true</IsChangeCameraWhenPathChange>
    <IsPathChange>false</IsPathChange>
    <IsStartVelocityConstant>true</IsStartVelocityConstant>
    <IsWallWalk>false</IsWallWalk>
    <IsYawUpdate>false</IsYawUpdate>
    <KeepVelocityDistance>5</KeepVelocityDistance>
    <OutOfControl>0.959999</OutOfControl>
    <m_IsConstantFrame>false</m_IsConstantFrame>
    <m_IsConstantPosition>true</m_IsConstantPosition>
    <m_IsMonkeyHunting>false</m_IsMonkeyHunting>
    <m_IsMonkeyHuntingLowAngle>true</m_IsMonkeyHuntingLowAngle>
    <m_IsStopBoost>false</m_IsStopBoost>
    <m_IsTo3D>false</m_IsTo3D>
    <m_MonkeyTarget>
      <x>-17.7204</x>
      <y>-57.6588</y>
      <z>-669.09</z>
    </m_MonkeyTarget>
    <Range>30</Range>
    <Position>
      <x>-17.7204</x>
      <y>-57.6588</y>
      <z>-669.09</z>
    </Position>
    <Rotation>
      <x>0.0616557</x>
      <y>-0.168891</y>
      <z>0.3061</z>
      <w>0.934866</w>
    </Rotation>
    <SetObjectID>2290</SetObjectID>
  </Spring>
  <ChangeVolumeCamera>
    <Collision_Height>70</Collision_Height>
    <Collision_Length>160</Collision_Length>
    <Collision_Width>160</Collision_Width>
    <DefaultStatus>0</DefaultStatus>
    <Ease_Time_Enter>2</Ease_Time_Enter>
    <Ease_Time_Leave>1</Ease_Time_Leave>
    <GroundOffset>0</GroundOffset>
    <IsCameraView>false</IsCameraView>
    <IsEnableCollision>false</IsEnableCollision>
    <LineType>0</LineType>
    <PositionList />
    <Priority>0</Priority>
    <Shape_Type>0</Shape_Type>
    <Target>
      <SetObjectID>2311</SetObjectID>
    </Target>
    <IsCastShadow>true</IsCastShadow>
    <Range>100</Range>
    <Position>
      <x>362.255</x>
      <y>45.3299</y>
      <z>85.3063</z>
    </Position>
    <Rotation>
      <x>0</x>
      <y>-0.266932</y>
      <z>0</z>
      <w>0.963715</w>
    </Rotation>
    <SetObjectID>2310</SetObjectID>
  </ChangeVolumeCamera>
  <ObjCameraParallel>
    <Distance>7</Distance>
    <Ease_Time_Enter>0</Ease_Time_Enter>
    <Ease_Time_Leave>0</Ease_Time_Leave>
    <Fovy>45</Fovy>
    <GroundOffset>0</GroundOffset>
    <IsCameraView>false</IsCameraView>
    <IsCollision>false</IsCollision>
    <IsControllable>false</IsControllable>
    <OffsetPitch>0</OffsetPitch>
    <OffsetYaw>0</OffsetYaw>
    <Pitch>30</Pitch>
    <Target>
      <SetObjectID>0</SetObjectID>
    </Target>
    <TargetOffset_Front>0</TargetOffset_Front>
    <TargetOffset_Right>0</TargetOffset_Right>
    <TargetOffset_Up>0</TargetOffset_Up>
    <TargetPositionFix>
      <x>0</x>
      <y>0</y>
      <z>0</z>
    </TargetPositionFix>
    <Target_Type>0</Target_Type>
    <Yaw>57</Yaw>
    <ZRot>0</ZRot>
    <IsCastShadow>true</IsCastShadow>
    <Range>100000</Range>
    <Position>
      <x>388.887</x>
      <y>61.6831</y>
      <z>105.401</z>
    </Position>
    <Rotation>
      <x>0</x>
      <y>0</y>
      <z>0</z>
      <w>1</w>
    </Rotation>
    <SetObjectID>2311</SetObjectID>
  </ObjCameraParallel>
  <ObjCameraParallel>
    <Distance>5</Distance>
    <Ease_Time_Enter>0</Ease_Time_Enter>
    <Ease_Time_Leave>0</Ease_Time_Leave>
    <Fovy>45</Fovy>
    <GroundOffset>0</GroundOffset>
    <IsCameraView>false</IsCameraView>
    <IsCollision>false</IsCollision>
    <IsControllable>false</IsControllable>
    <OffsetPitch>0</OffsetPitch>
    <OffsetYaw>0</OffsetYaw>
    <Pitch>0</Pitch>
    <Target>
      <SetObjectID>0</SetObjectID>
    </Target>
    <TargetOffset_Front>0</TargetOffset_Front>
    <TargetOffset_Right>0</TargetOffset_Right>
    <TargetOffset_Up>0.3</TargetOffset_Up>
    <TargetPositionFix>
      <x>0</x>
      <y>0</y>
      <z>0</z>
    </TargetPositionFix>
    <Target_Type>0</Target_Type>
    <Yaw>60</Yaw>
    <ZRot>0</ZRot>
    <IsCastShadow>true</IsCastShadow>
    <Range>100000</Range>
    <Position>
      <x>391.283</x>
      <y>46.21</y>
      <z>102.251</z>
    </Position>
    <Rotation>
      <x>0</x>
      <y>0</y>
      <z>0</z>
      <w>1</w>
    </Rotation>
    <SetObjectID>2312</SetObjectID>
  </ObjCameraParallel>
  <ChangeVolumeCamera>
    <Collision_Height>79</Collision_Height>
    <Collision_Length>183</Collision_Length>
    <Collision_Width>109</Collision_Width>
    <DefaultStatus>0</DefaultStatus>
    <Ease_Time_Enter>1.5</Ease_Time_Enter>
    <Ease_Time_Leave>1.5</Ease_Time_Leave>
    <GroundOffset>0</GroundOffset>
    <IsCameraView>false</IsCameraView>
    <IsEnableCollision>false</IsEnableCollision>
    <LineType>0</LineType>
    <PositionList />
    <Priority>0</Priority>
    <Shape_Type>0</Shape_Type>
    <Target>
      <SetObjectID>2332</SetObjectID>
    </Target>
    <IsCastShadow>true</IsCastShadow>
    <Range>100</Range>
    <Position>
      <x>117.148</x>
      <y>10.8501</y>
      <z>-127.92</z>
    </Position>
    <Rotation>
      <x>0</x>
      <y>0.288162</y>
      <z>0</z>
      <w>0.957582</w>
    </Rotation>
    <SetObjectID>2331</SetObjectID>
  </ChangeVolumeCamera>
  <ObjCameraParallel>
    <Distance>5</Distance>
    <Ease_Time_Enter>0</Ease_Time_Enter>
    <Ease_Time_Leave>0</Ease_Time_Leave>
    <Fovy>45</Fovy>
    <GroundOffset>0</GroundOffset>
    <IsCameraView>false</IsCameraView>
    <IsCollision>false</IsCollision>
    <IsControllable>false</IsControllable>
    <OffsetPitch>0</OffsetPitch>
    <OffsetYaw>0</OffsetYaw>
    <Pitch>15.033</Pitch>
    <Target>
      <SetObjectID>0</SetObjectID>
    </Target>
    <TargetOffset_Front>0</TargetOffset_Front>
    <TargetOffset_Right>0</TargetOffset_Right>
    <TargetOffset_Up>0</TargetOffset_Up>
    <TargetPositionFix>
      <x>0</x>
      <y>0</y>
      <z>0</z>
    </TargetPositionFix>
    <Target_Type>0</Target_Type>
    <Yaw>33.7082</Yaw>
    <ZRot>0</ZRot>
    <IsCastShadow>true</IsCastShadow>
    <Range>100000</Range>
    <Position>
      <x>127.582</x>
      <y>17.3397</y>
      <z>-116.605</z>
    </Position>
    <Rotation>
      <x>0</x>
      <y>0</y>
      <z>0</z>
      <w>1</w>
    </Rotation>
    <SetObjectID>2332</SetObjectID>
  </ObjCameraParallel>
  <ObjCameraParallel>
    <Distance>8.18536</Distance>
    <Ease_Time_Enter>0</Ease_Time_Enter>
    <Ease_Time_Leave>0</Ease_Time_Leave>
    <Fovy>45</Fovy>
    <GroundOffset>0</GroundOffset>
    <IsCameraView>false</IsCameraView>
    <IsCollision>false</IsCollision>
    <IsControllable>false</IsControllable>
    <OffsetPitch>0</OffsetPitch>
    <OffsetYaw>0</OffsetYaw>
    <Pitch>28.0742</Pitch>
    <Target>
      <SetObjectID>0</SetObjectID>
    </Target>
    <TargetOffset_Front>1.4</TargetOffset_Front>
    <TargetOffset_Right>0</TargetOffset_Right>
    <TargetOffset_Up>0</TargetOffset_Up>
    <TargetPositionFix>
      <x>0</x>
      <y>0</y>
      <z>0</z>
    </TargetPositionFix>
    <Target_Type>0</Target_Type>
    <Yaw>34.4326</Yaw>
    <ZRot>0</ZRot>
    <IsCastShadow>true</IsCastShadow>
    <Range>100000</Range>
    <Position>
      <x>74.4803</x>
      <y>0.866677</y>
      <z>-202.57</z>
    </Position>
    <Rotation>
      <x>0</x>
      <y>0</y>
      <z>0</z>
      <w>1</w>
    </Rotation>
    <SetObjectID>2349</SetObjectID>
  </ObjCameraParallel>
  <ChangeVolumeCamera>
    <Collision_Height>108</Collision_Height>
    <Collision_Length>132</Collision_Length>
    <Collision_Width>91</Collision_Width>
    <DefaultStatus>0</DefaultStatus>
    <Ease_Time_Enter>1.5</Ease_Time_Enter>
    <Ease_Time_Leave>1.5</Ease_Time_Leave>
    <GroundOffset>0</GroundOffset>
    <IsCameraView>false</IsCameraView>
    <IsEnableCollision>false</IsEnableCollision>
    <LineType>0</LineType>
    <PositionList />
    <Priority>0</Priority>
    <Shape_Type>0</Shape_Type>
    <Target>
      <SetObjectID>2349</SetObjectID>
    </Target>
    <IsCastShadow>true</IsCastShadow>
    <Range>100</Range>
    <Position>
      <x>45.6379</x>
      <y>8.87643</y>
      <z>-240.696</z>
    </Position>
    <Rotation>
      <x>0</x>
      <y>0.247356</y>
      <z>0</z>
      <w>0.968925</w>
    </Rotation>
    <SetObjectID>2350</SetObjectID>
  </ChangeVolumeCamera>
  <ChangeVolumeCamera>
    <Collision_Height>49</Collision_Height>
    <Collision_Length>96</Collision_Length>
    <Collision_Width>54</Collision_Width>
    <DefaultStatus>0</DefaultStatus>
    <Ease_Time_Enter>1.3</Ease_Time_Enter>
    <Ease_Time_Leave>1.3</Ease_Time_Leave>
    <GroundOffset>0</GroundOffset>
    <IsCameraView>false</IsCameraView>
    <IsEnableCollision>false</IsEnableCollision>
    <LineType>0</LineType>
    <PositionList />
    <Priority>1</Priority>
    <Shape_Type>0</Shape_Type>
    <Target>
      <SetObjectID>2312</SetObjectID>
    </Target>
    <IsCastShadow>true</IsCastShadow>
    <Range>100</Range>
    <Position>
      <x>413.995</x>
      <y>53.8884</y>
      <z>115.001</z>
    </Position>
    <Rotation>
      <x>0.0156393</x>
      <y>-0.310573</y>
      <z>8.19104e-05</z>
      <w>0.950422</w>
    </Rotation>
    <SetObjectID>2361</SetObjectID>
  </ChangeVolumeCamera>
  <ChangeMode_3Dto2D>
    <Collision_Height>100</Collision_Height>
    <Collision_Width>32</Collision_Width>
    <GroundOffset>0</GroundOffset>
    <TargetDirection>
      <x>10.8074</x>
      <y>-68.5676</y>
      <z>-352.044</z>
    </TargetDirection>
    <m_IsChangeCamera>false</m_IsChangeCamera>
    <m_IsEnableFromBack>true</m_IsEnableFromBack>
    <m_IsEnableFromFront>true</m_IsEnableFromFront>
    <m_IsPadCorrect>true</m_IsPadCorrect>
    <m_PathEaseTime>1</m_PathEaseTime>
    <IsCastShadow>true</IsCastShadow>
    <Range>100</Range>
    <Position>
      <x>13.6563</x>
      <y>-18.0028</y>
      <z>-336.844</z>
    </Position>
    <Rotation>
      <x>0</x>
      <y>0.999588</y>
      <z>0</z>
      <w>0.0287097</w>
    </Rotation>
    <SetObjectID>2364</SetObjectID>
  </ChangeMode_3Dto2D>
  <ObjCameraPan>
    <CameraPositionMode>0</CameraPositionMode>
    <Distance>5</Distance>
    <Ease_Time_Enter>0</Ease_Time_Enter>
    <Ease_Time_Leave>0</Ease_Time_Leave>
    <FaceType>0</FaceType>
    <Fovy>45</Fovy>
    <GroundOffset>0</GroundOffset>
    <IsCameraView>false</IsCameraView>
    <IsCollision>false</IsCollision>
    <IsControllable>false</IsControllable>
    <OffsetPitch>0</OffsetPitch>
    <OffsetYaw>0</OffsetYaw>
    <Radius>1</Radius>
    <Target>
      <SetObjectID>0</SetObjectID>
    </Target>
    <TargetOffset_Front>0</TargetOffset_Front>
    <TargetOffset_Right>0</TargetOffset_Right>
    <TargetOffset_Up>0</TargetOffset_Up>
    <TargetPositionFix>
      <x>0</x>
      <y>0</y>
      <z>0</z>
    </TargetPositionFix>
    <Target_Type>0</Target_Type>
    <ZRot>0</ZRot>
    <IsCastShadow>true</IsCastShadow>
    <Range>100000</Range>
    <Position>
      <x>29.6463</x>
      <y>-64.6263</y>
      <z>-354.408</z>
    </Position>
    <Rotation>
      <x>0</x>
      <y>0</y>
      <z>0</z>
      <w>1</w>
    </Rotation>
    <SetObjectID>2366</SetObjectID>
  </ObjCameraPan>
  <ChangeMode_3Dto2D>
    <Collision_Height>100</Collision_Height>
    <Collision_Width>50</Collision_Width>
    <GroundOffset>0</GroundOffset>
    <TargetDirection>
      <x>21.3686</x>
      <y>-68.1665</y>
      <z>-345.309</z>
    </TargetDirection>
    <m_IsChangeCamera>false</m_IsChangeCamera>
    <m_IsEnableFromBack>true</m_IsEnableFromBack>
    <m_IsEnableFromFront>true</m_IsEnableFromFront>
    <m_IsPadCorrect>true</m_IsPadCorrect>
    <m_PathEaseTime>1</m_PathEaseTime>
    <IsCastShadow>true</IsCastShadow>
    <Range>100</Range>
    <Position>
      <x>21.8872</x>
      <y>-24.1167</y>
      <z>-362.932</z>
    </Position>
    <Rotation>
      <x>0</x>
      <y>0</y>
      <z>0</z>
      <w>1</w>
    </Rotation>
    <SetObjectID>2367</SetObjectID>
  </ChangeMode_3Dto2D>
  <ChangeVolumeCamera>
    <Collision_Height>92</Collision_Height>
    <Collision_Length>60</Collision_Length>
    <Collision_Width>105</Collision_Width>
    <DefaultStatus>0</DefaultStatus>
    <Ease_Time_Enter>0.3</Ease_Time_Enter>
    <Ease_Time_Leave>1</Ease_Time_Leave>
    <GroundOffset>0</GroundOffset>
    <IsCameraView>false</IsCameraView>
    <IsEnableCollision>false</IsEnableCollision>
    <LineType>0</LineType>
    <PositionList />
    <Priority>0</Priority>
    <Shape_Type>0</Shape_Type>
    <Target>
      <SetObjectID>0</SetObjectID>
    </Target>
    <IsCastShadow>true</IsCastShadow>
    <Range>100</Range>
    <Position>
      <x>20.2516</x>
      <y>-62.3694</y>
      <z>-485.19</z>
    </Position>
    <Rotation>
      <x>0</x>
      <y>0</y>
      <z>0</z>
      <w>1</w>
    </Rotation>
    <SetObjectID>2372</SetObjectID>
  </ChangeVolumeCamera>
  <ObjCameraPoint>
    <Distance>10</Distance>
    <Ease_Time_Enter>0</Ease_Time_Enter>
    <Ease_Time_Leave>0</Ease_Time_Leave>
    <Fovy>45</Fovy>
    <GroundOffset>0</GroundOffset>
    <IsCameraView>false</IsCameraView>
    <IsCollision>true</IsCollision>
    <IsControllable>true</IsControllable>
    <Target>
      <SetObjectID>0</SetObjectID>
    </Target>
    <TargetOffset_Front>0</TargetOffset_Front>
    <TargetOffset_Right>0</TargetOffset_Right>
    <TargetOffset_Up>0</TargetOffset_Up>
    <TargetPositionFix>
      <x>0</x>
      <y>0</y>
      <z>0</z>
    </TargetPositionFix>
    <Target_Type>0</Target_Type>
    <ZRot>0</ZRot>
    <IsCastShadow>true</IsCastShadow>
    <Range>100000</Range>
    <Position>
      <x>4.49164</x>
      <y>-39.9431</y>
      <z>-595.583</z>
    </Position>
    <Rotation>
      <x>0</x>
      <y>0</y>
      <z>0</z>
      <w>1</w>
    </Rotation>
    <SetObjectID>2373</SetObjectID>
  </ObjCameraPoint>
  <ObjCameraParallel>
    <Distance>6</Distance>
    <Ease_Time_Enter>0</Ease_Time_Enter>
    <Ease_Time_Leave>0</Ease_Time_Leave>
    <Fovy>45</Fovy>
    <GroundOffset>0</GroundOffset>
    <IsCameraView>false</IsCameraView>
    <IsCollision>true</IsCollision>
    <IsControllable>false</IsControllable>
    <OffsetPitch>0</OffsetPitch>
    <OffsetYaw>0</OffsetYaw>
    <Pitch>10</Pitch>
    <Target>
      <SetObjectID>0</SetObjectID>
    </Target>
    <TargetOffset_Front>0</TargetOffset_Front>
    <TargetOffset_Right>0</TargetOffset_Right>
    <TargetOffset_Up>0</TargetOffset_Up>
    <TargetPositionFix>
      <x>0</x>
      <y>0</y>
      <z>0</z>
    </TargetPositionFix>
    <Target_Type>0</Target_Type>
    <Yaw>0</Yaw>
    <ZRot>0</ZRot>
    <IsCastShadow>true</IsCastShadow>
    <Range>100000</Range>
    <Position>
      <x>21.0386</x>
      <y>-66.2939</y>
      <z>-619.663</z>
    </Position>
    <Rotation>
      <x>0</x>
      <y>0</y>
      <z>0</z>
      <w>1</w>
    </Rotation>
    <SetObjectID>2374</SetObjectID>
  </ObjCameraParallel>
  <ChangeVolumeCamera>
    <Collision_Height>74</Collision_Height>
    <Collision_Length>137</Collision_Length>
    <Collision_Width>77</Collision_Width>
    <DefaultStatus>0</DefaultStatus>
    <Ease_Time_Enter>1</Ease_Time_Enter>
    <Ease_Time_Leave>1.5</Ease_Time_Leave>
    <GroundOffset>0</GroundOffset>
    <IsCameraView>false</IsCameraView>
    <IsEnableCollision>false</IsEnableCollision>
    <LineType>0</LineType>
    <PositionList />
    <Priority>1</Priority>
    <Shape_Type>0</Shape_Type>
    <Target>
      <SetObjectID>2374</SetObjectID>
    </Target>
    <IsCastShadow>true</IsCastShadow>
    <Range>100</Range>
    <Position>
      <x>16.8516</x>
      <y>-59.5921</y>
      <z>-591.161</z>
    </Position>
    <Rotation>
      <x>0</x>
      <y>0</y>
      <z>0</z>
      <w>1</w>
    </Rotation>
    <SetObjectID>2375</SetObjectID>
  </ChangeVolumeCamera>
  <ObjCameraParallel>
    <Distance>6</Distance>
    <Ease_Time_Enter>0</Ease_Time_Enter>
    <Ease_Time_Leave>0</Ease_Time_Leave>
    <Fovy>45</Fovy>
    <GroundOffset>0</GroundOffset>
    <IsCameraView>true</IsCameraView>
    <IsCollision>false</IsCollision>
    <IsControllable>false</IsControllable>
    <OffsetPitch>0</OffsetPitch>
    <OffsetYaw>0</OffsetYaw>
    <Pitch>15</Pitch>
    <Target>
      <SetObjectID>0</SetObjectID>
    </Target>
    <TargetOffset_Front>0</TargetOffset_Front>
    <TargetOffset_Right>0</TargetOffset_Right>
    <TargetOffset_Up>0.5</TargetOffset_Up>
    <TargetPositionFix>
      <x>0</x>
      <y>0</y>
      <z>0</z>
    </TargetPositionFix>
    <Target_Type>0</Target_Type>
    <Yaw>89.5</Yaw>
    <ZRot>0</ZRot>
    <IsCastShadow>true</IsCastShadow>
    <Range>100000</Range>
    <Position>
      <x>-117.291</x>
      <y>-56.1394</y>
      <z>-671.095</z>
    </Position>
    <Rotation>
      <x>0</x>
      <y>0</y>
      <z>0</z>
      <w>1</w>
    </Rotation>
    <SetObjectID>2386</SetObjectID>
  </ObjCameraParallel>
  <ChangeVolumeCamera>
    <Collision_Height>35</Collision_Height>
    <Collision_Length>57</Collision_Length>
    <Collision_Width>61</Collision_Width>
    <DefaultStatus>0</DefaultStatus>
    <Ease_Time_Enter>1.5</Ease_Time_Enter>
    <Ease_Time_Leave>1.5</Ease_Time_Leave>
    <GroundOffset>0</GroundOffset>
    <IsCameraView>false</IsCameraView>
    <IsEnableCollision>false</IsEnableCollision>
    <LineType>0</LineType>
    <PositionList />
    <Priority>0</Priority>
    <Shape_Type>0</Shape_Type>
    <Target>
      <SetObjectID>2389</SetObjectID>
    </Target>
    <IsCastShadow>true</IsCastShadow>
    <Range>100</Range>
    <Position>
      <x>-209.791</x>
      <y>-45.8602</y>
      <z>-681.005</z>
    </Position>
    <Rotation>
      <x>0</x>
      <y>0</y>
      <z>0</z>
      <w>1</w>
    </Rotation>
    <SetObjectID>2390</SetObjectID>
  </ChangeVolumeCamera>
  <ChangeMode_3Dto2D>
    <Collision_Height>40</Collision_Height>
    <Collision_Width>10</Collision_Width>
    <GroundOffset>0</GroundOffset>
    <TargetDirection>
      <x>-205.861</x>
      <y>-82.2756</y>
      <z>-1305.56</z>
    </TargetDirection>
    <m_IsChangeCamera>false</m_IsChangeCamera>
    <m_IsEnableFromBack>true</m_IsEnableFromBack>
    <m_IsEnableFromFront>true</m_IsEnableFromFront>
    <m_IsPadCorrect>true</m_IsPadCorrect>
    <m_PathEaseTime>1</m_PathEaseTime>
    <IsCastShadow>true</IsCastShadow>
    <Range>100</Range>
    <Position>
      <x>-206.035</x>
      <y>-82.7687</y>
      <z>-1295.47</z>
    </Position>
    <Rotation>
      <x>0</x>
      <y>1</y>
      <z>0</z>
      <w>0</w>
    </Rotation>
    <SetObjectID>2406</SetObjectID>
  </ChangeMode_3Dto2D>
  <ChangeMode_3Dto2D>
    <Collision_Height>40</Collision_Height>
    <Collision_Width>10</Collision_Width>
    <GroundOffset>0</GroundOffset>
    <TargetDirection>
      <x>-411.204</x>
      <y>0</y>
      <z>-2901.17</z>
    </TargetDirection>
    <m_IsChangeCamera>false</m_IsChangeCamera>
    <m_IsEnableFromBack>true</m_IsEnableFromBack>
    <m_IsEnableFromFront>true</m_IsEnableFromFront>
    <m_IsPadCorrect>true</m_IsPadCorrect>
    <m_PathEaseTime>1</m_PathEaseTime>
    <IsCastShadow>true</IsCastShadow>
    <Range>100</Range>
    <Position>
      <x>-206.051</x>
      <y>-82.7687</y>
      <z>-1444.13</z>
    </Position>
    <Rotation>
      <x>0</x>
      <y>0</y>
      <z>0</z>
      <w>1</w>
    </Rotation>
    <SetObjectID>2407</SetObjectID>
  </ChangeMode_3Dto2D>
  <ObjCameraParallel>
    <Distance>8</Distance>
    <Ease_Time_Enter>0</Ease_Time_Enter>
    <Ease_Time_Leave>0</Ease_Time_Leave>
    <Fovy>45</Fovy>
    <GroundOffset>0</GroundOffset>
    <IsCameraView>false</IsCameraView>
    <IsCollision>false</IsCollision>
    <IsControllable>false</IsControllable>
    <OffsetPitch>0</OffsetPitch>
    <OffsetYaw>0</OffsetYaw>
    <Pitch>27</Pitch>
    <Target>
      <SetObjectID>0</SetObjectID>
    </Target>
    <TargetOffset_Front>0</TargetOffset_Front>
    <TargetOffset_Right>0</TargetOffset_Right>
    <TargetOffset_Up>1</TargetOffset_Up>
    <TargetPositionFix>
      <x>0</x>
      <y>0</y>
      <z>0</z>
    </TargetPositionFix>
    <Target_Type>0</Target_Type>
    <Yaw>0</Yaw>
    <ZRot>0</ZRot>
    <IsCastShadow>true</IsCastShadow>
    <Range>100000</Range>
    <Position>
      <x>-202.853</x>
      <y>-79.8245</y>
      <z>-1503.86</z>
    </Position>
    <Rotation>
      <x>0</x>
      <y>0</y>
      <z>0</z>
      <w>1</w>
    </Rotation>
    <SetObjectID>2408</SetObjectID>
  </ObjCameraParallel>
  <ChangeVolumeCamera>
    <Collision_Height>51</Collision_Height>
    <Collision_Length>137</Collision_Length>
    <Collision_Width>64</Collision_Width>
    <DefaultStatus>0</DefaultStatus>
    <Ease_Time_Enter>1.5</Ease_Time_Enter>
    <Ease_Time_Leave>1.5</Ease_Time_Leave>
    <GroundOffset>0</GroundOffset>
    <IsCameraView>false</IsCameraView>
    <IsEnableCollision>false</IsEnableCollision>
    <LineType>0</LineType>
    <PositionList />
    <Priority>0</Priority>
    <Shape_Type>0</Shape_Type>
    <Target>
      <SetObjectID>2408</SetObjectID>
    </Target>
    <IsCastShadow>true</IsCastShadow>
    <Range>100</Range>
    <Position>
      <x>-205.112</x>
      <y>-79.8245</y>
      <z>-1515.31</z>
    </Position>
    <Rotation>
      <x>0</x>
      <y>0</y>
      <z>0</z>
      <w>1</w>
    </Rotation>
    <SetObjectID>2409</SetObjectID>
  </ChangeVolumeCamera>
  <HintRing>
    <Category>0</Category>
    <CharaType>1</CharaType>
    <EventOff>0</EventOff>
    <EventOff2>0</EventOff2>
    <EventOn>0</EventOn>
    <EventOn2>0</EventOn2>
    <ExistPlatform>false</ExistPlatform>
    <GroundOffset>0</GroundOffset>
    <GroupID>WhiteIsland_ACT1_003</GroupID>
    <NeedInput>true</NeedInput>
    <PlayerStop>true</PlayerStop>
    <TargetListOff />
    <TargetListOff2 />
    <TargetListOn />
    <TargetListOn2 />
    <TimerOff>0</TimerOff>
    <TimerOff2>0</TimerOff2>
    <TimerOn>0</TimerOn>
    <TimerOn2>0</TimerOn2>
    <UsePicture>true</UsePicture>
    <WaitEvent>false</WaitEvent>
    <Position>
      <x>-176.756</x>
      <y>-49.677</y>
      <z>-679.075</z>
    </Position>
    <Rotation>
      <x>0</x>
      <y>0.505922</y>
      <z>0</z>
      <w>0.862579</w>
    </Rotation>
    <SetObjectID>12309</SetObjectID>
  </HintRing>
  <HintRing>
    <Category>0</Category>
    <CharaType>1</CharaType>
    <EventOff>0</EventOff>
    <EventOff2>0</EventOff2>
    <EventOn>0</EventOn>
    <EventOn2>0</EventOn2>
    <ExistPlatform>false</ExistPlatform>
    <GroundOffset>0</GroundOffset>
    <GroupID>WhiteIsland_ACT1_005</GroupID>
    <NeedInput>true</NeedInput>
    <PlayerStop>true</PlayerStop>
    <TargetListOff />
    <TargetListOff2 />
    <TargetListOn />
    <TargetListOn2 />
    <TimerOff>0</TimerOff>
    <TimerOff2>0</TimerOff2>
    <TimerOn>0</TimerOn>
    <TimerOn2>0</TimerOn2>
    <UsePicture>false</UsePicture>
    <WaitEvent>false</WaitEvent>
    <Position>
      <x>23.7746</x>
      <y>-61.4994</y>
      <z>-631.927</z>
    </Position>
    <Rotation>
      <x>0</x>
      <y>0</y>
      <z>0</z>
      <w>1</w>
    </Rotation>
    <SetObjectID>12311</SetObjectID>
  </HintRing>
  <HintRing>
    <Category>0</Category>
    <CharaType>1</CharaType>
    <EventOff>0</EventOff>
    <EventOff2>0</EventOff2>
    <EventOn>0</EventOn>
    <EventOn2>0</EventOn2>
    <ExistPlatform>false</ExistPlatform>
    <GroundOffset>0</GroundOffset>
    <GroupID>WhiteIsland_ACT1_006</GroupID>
    <NeedInput>true</NeedInput>
    <PlayerStop>true</PlayerStop>
    <TargetListOff />
    <TargetListOff2 />
    <TargetListOn />
    <TargetListOn2 />
    <TimerOff>0</TimerOff>
    <TimerOff2>0</TimerOff2>
    <TimerOn>0</TimerOn>
    <TimerOn2>0</TimerOn2>
    <UsePicture>true</UsePicture>
    <WaitEvent>false</WaitEvent>
    <Position>
      <x>24.0558</x>
      <y>-68.1719</y>
      <z>-619.286</z>
    </Position>
    <Rotation>
      <x>0.0628668</x>
      <y>0</y>
      <z>0.0182942</z>
      <w>0.997854</w>
    </Rotation>
    <SetObjectID>12312</SetObjectID>
  </HintRing>
  <HintRing>
    <Category>0</Category>
    <CharaType>1</CharaType>
    <EventOff>0</EventOff>
    <EventOff2>0</EventOff2>
    <EventOn>0</EventOn>
    <EventOn2>0</EventOn2>
    <ExistPlatform>false</ExistPlatform>
    <GroundOffset>0</GroundOffset>
    <GroupID>WhiteIsland_ACT1_007</GroupID>
    <NeedInput>true</NeedInput>
    <PlayerStop>true</PlayerStop>
    <TargetListOff />
    <TargetListOff2 />
    <TargetListOn />
    <TargetListOn2 />
    <TimerOff>0</TimerOff>
    <TimerOff2>0</TimerOff2>
    <TimerOn>0</TimerOn>
    <TimerOn2>0</TimerOn2>
    <UsePicture>true</UsePicture>
    <WaitEvent>false</WaitEvent>
    <Position>
      <x>18.9713</x>
      <y>-60.2642</y>
      <z>-639.167</z>
    </Position>
    <Rotation>
      <x>0</x>
      <y>0</y>
      <z>0</z>
      <w>1</w>
    </Rotation>
    <SetObjectID>12313</SetObjectID>
  </HintRing>
  <HintRing>
    <Category>0</Category>
    <CharaType>1</CharaType>
    <EventOff>0</EventOff>
    <EventOff2>0</EventOff2>
    <EventOn>0</EventOn>
    <EventOn2>0</EventOn2>
    <ExistPlatform>false</ExistPlatform>
    <GroundOffset>0</GroundOffset>
    <GroupID>WhiteIsland_ACT1_008</GroupID>
    <NeedInput>true</NeedInput>
    <PlayerStop>true</PlayerStop>
    <TargetListOff />
    <TargetListOff2 />
    <TargetListOn />
    <TargetListOn2 />
    <TimerOff>0</TimerOff>
    <TimerOff2>0</TimerOff2>
    <TimerOn>0</TimerOn>
    <TimerOn2>0</TimerOn2>
    <UsePicture>true</UsePicture>
    <WaitEvent>false</WaitEvent>
    <Position>
      <x>11.162</x>
      <y>-57.6294</y>
      <z>-667.281</z>
    </Position>
    <Rotation>
      <x>0.00198294</x>
      <y>0.710011</y>
      <z>-0.00222397</z>
      <w>0.704183</w>
    </Rotation>
    <SetObjectID>12314</SetObjectID>
  </HintRing>
  <HintRing>
    <Category>0</Category>
    <CharaType>1</CharaType>
    <EventOff>0</EventOff>
    <EventOff2>0</EventOff2>
    <EventOn>0</EventOn>
    <EventOn2>0</EventOn2>
    <ExistPlatform>false</ExistPlatform>
    <GroundOffset>0</GroundOffset>
    <GroupID>WhiteIsland_ACT1_010</GroupID>
    <NeedInput>true</NeedInput>
    <PlayerStop>true</PlayerStop>
    <TargetListOff />
    <TargetListOff2 />
    <TargetListOn />
    <TargetListOn2 />
    <TimerOff>0</TimerOff>
    <TimerOff2>0</TimerOff2>
    <TimerOn>0</TimerOn>
    <TimerOn2>0</TimerOn2>
    <UsePicture>true</UsePicture>
    <WaitEvent>false</WaitEvent>
    <Position>
      <x>-98.152</x>
      <y>-57.6748</y>
      <z>-671.439</z>
    </Position>
    <Rotation>
      <x>0</x>
      <y>0.612032</y>
      <z>0</z>
      <w>0.790833</w>
    </Rotation>
    <SetObjectID>12316</SetObjectID>
  </HintRing>
  <HintRing>
    <Category>0</Category>
    <CharaType>1</CharaType>
    <EventOff>0</EventOff>
    <EventOff2>0</EventOff2>
    <EventOn>0</EventOn>
    <EventOn2>0</EventOn2>
    <ExistPlatform>false</ExistPlatform>
    <GroundOffset>0</GroundOffset>
    <GroupID>WhiteIsland_ACT1_011</GroupID>
    <NeedInput>true</NeedInput>
    <PlayerStop>true</PlayerStop>
    <TargetListOff />
    <TargetListOff2 />
    <TargetListOn />
    <TargetListOn2 />
    <TimerOff>0</TimerOff>
    <TimerOff2>0</TimerOff2>
    <TimerOn>0</TimerOn>
    <TimerOn2>0</TimerOn2>
    <UsePicture>false</UsePicture>
    <WaitEvent>false</WaitEvent>
    <Position>
      <x>-110.378</x>
      <y>-57.3559</y>
      <z>-667.433</z>
    </Position>
    <Rotation>
      <x>0</x>
      <y>0.600223</y>
      <z>0</z>
      <w>0.799833</w>
    </Rotation>
    <SetObjectID>12317</SetObjectID>
  </HintRing>
  <HintRing>
    <Category>0</Category>
    <CharaType>1</CharaType>
    <EventOff>0</EventOff>
    <EventOff2>0</EventOff2>
    <EventOn>0</EventOn>
    <EventOn2>0</EventOn2>
    <ExistPlatform>false</ExistPlatform>
    <GroundOffset>0</GroundOffset>
    <GroupID>WhiteIsland_ACT1_014</GroupID>
    <NeedInput>true</NeedInput>
    <PlayerStop>true</PlayerStop>
    <TargetListOff />
    <TargetListOff2 />
    <TargetListOn />
    <TargetListOn2 />
    <TimerOff>0</TimerOff>
    <TimerOff2>0</TimerOff2>
    <TimerOn>0</TimerOn>
    <TimerOn2>0</TimerOn2>
    <UsePicture>false</UsePicture>
    <WaitEvent>false</WaitEvent>
    <Position>
      <x>384.319</x>
      <y>46.5434</y>
      <z>97.8839</z>
    </Position>
    <Rotation>
      <x>0</x>
      <y>0.50703</y>
      <z>0</z>
      <w>0.861928</w>
    </Rotation>
    <SetObjectID>12320</SetObjectID>
  </HintRing>
  <HintRing>
    <Category>0</Category>
    <CharaType>1</CharaType>
    <EventOff>0</EventOff>
    <EventOff2>0</EventOff2>
    <EventOn>0</EventOn>
    <EventOn2>0</EventOn2>
    <ExistPlatform>false</ExistPlatform>
    <GroundOffset>0</GroundOffset>
    <GroupID>WhiteIsland_ACT1_015</GroupID>
    <NeedInput>true</NeedInput>
    <PlayerStop>true</PlayerStop>
    <TargetListOff />
    <TargetListOff2 />
    <TargetListOn />
    <TargetListOn2 />
    <TimerOff>0</TimerOff>
    <TimerOff2>0</TimerOff2>
    <TimerOn>0</TimerOn>
    <TimerOn2>0</TimerOn2>
    <UsePicture>true</UsePicture>
    <WaitEvent>false</WaitEvent>
    <Position>
      <x>-203.537</x>
      <y>-44.4154</y>
      <z>-709.82</z>
    </Position>
    <Rotation>
      <x>0</x>
      <y>0</y>
      <z>0</z>
      <w>1</w>
    </Rotation>
    <SetObjectID>12321</SetObjectID>
  </HintRing>
  <HintRing>
    <Category>0</Category>
    <CharaType>1</CharaType>
    <EventOff>0</EventOff>
    <EventOff2>0</EventOff2>
    <EventOn>0</EventOn>
    <EventOn2>0</EventOn2>
    <ExistPlatform>false</ExistPlatform>
    <GroundOffset>0</GroundOffset>
    <GroupID>WhiteIsland_ACT1_016</GroupID>
    <NeedInput>true</NeedInput>
    <PlayerStop>true</PlayerStop>
    <TargetListOff />
    <TargetListOff2 />
    <TargetListOn />
    <TargetListOn2 />
    <TimerOff>0</TimerOff>
    <TimerOff2>0</TimerOff2>
    <TimerOn>0</TimerOn>
    <TimerOn2>0</TimerOn2>
    <UsePicture>true</UsePicture>
    <WaitEvent>false</WaitEvent>
    <Position>
      <x>-203.255</x>
      <y>-84.0331</y>
      <z>-1515.47</z>
    </Position>
    <Rotation>
      <x>0</x>
      <y>0</y>
      <z>0</z>
      <w>1</w>
    </Rotation>
    <SetObjectID>12322</SetObjectID>
  </HintRing>
  <PointMarker>
    <GroundOffset>0</GroundOffset>
    <StageType>0</StageType>
    <Width>2.5</Width>
    <Height>5</Height>
    <Position>
      <x>-95.895</x>
      <y>-58.8608</y>
      <z>-668.91</z>
    </Position>
    <Rotation>
      <x>-0.0352678</x>
      <y>-0.694584</y>
      <z>0.0256674</z>
      <w>0.718078</w>
    </Rotation>
    <SetObjectID>12323</SetObjectID>
  </PointMarker>
  <Hint>
    <Category>0</Category>
    <ChangeTime>-0.1</ChangeTime>
    <CharaType>1</CharaType>
    <DrawCharWait>-0.01</DrawCharWait>
    <DrawOnce>true</DrawOnce>
    <EndWait>-0.1</EndWait>
    <ExistPlatform>false</ExistPlatform>
    <GroundOffset>0</GroundOffset>
    <GroupID>WhiteIsland_ACT1_002</GroupID>
    <NeedInput>true</NeedInput>
    <PlayerStop>false</PlayerStop>
    <UsePicture>false</UsePicture>
    <Position>
      <x>388.036</x>
      <y>45.7752</y>
      <z>102.05</z>
    </Position>
    <Rotation>
      <x>0</x>
      <y>0</y>
      <z>0</z>
      <w>1</w>
    </Rotation>
    <SetObjectID>12361</SetObjectID>
  </Hint>
  <EventCollision>
    <Collision_Height>15</Collision_Height>
    <Collision_Length>71</Collision_Length>
    <Collision_Width>2.1</Collision_Width>
    <DefaultStatus>0</DefaultStatus>
    <Durability>0</Durability>
    <Event0>6</Event0>
    <Event1>0</Event1>
    <Event2>0</Event2>
    <Event3>0</Event3>
    <GroundOffset>0</GroundOffset>
    <Shape_Type>0</Shape_Type>
    <TargetList0>
      <SetObjectID>12361</SetObjectID>
    </TargetList0>
    <TargetList1 />
    <TargetList2 />
    <TargetList3 />
    <Timer0>0</Timer0>
    <Timer1>0</Timer1>
    <Timer2>0</Timer2>
    <Timer3>0</Timer3>
    <Trigger>
      <SetObjectID>0</SetObjectID>
    </Trigger>
    <TriggerType>0</TriggerType>
    <Position>
      <x>389.891</x>
      <y>48.0891</y>
      <z>102.938</z>
    </Position>
    <Rotation>
      <x>0.0384497</x>
      <y>-0.409809</y>
      <z>0.000113992</z>
      <w>0.91136</w>
    </Rotation>
    <SetObjectID>12363</SetObjectID>
  </EventCollision>
  <Ring>
    <GroundOffset>0</GroundOffset>
    <IsLightSpeedDashTarget>true</IsLightSpeedDashTarget>
    <IsReset>false</IsReset>
    <ResetTime>0</ResetTime>
    <IsCastShadow>true</IsCastShadow>
    <Range>100</Range>
    <Position>
      <x>-99.4106</x>
      <y>-58.367</y>
      <z>-669.19</z>
    </Position>
    <Rotation>
      <x>0</x>
      <y>0.732348</y>
      <z>0</z>
      <w>-0.68093</w>
    </Rotation>
    <SetObjectID>12364</SetObjectID>
    <MultiSetParam>
      <Element>
        <Index>1</Index>
        <Position>
          <x>-101.405</x>
          <y>-58.3541</y>
          <z>-669.336</z>
        </Position>
        <Rotation>
          <x>0</x>
          <y>0.732348</y>
          <z>0</z>
          <w>-0.68093</w>
        </Rotation>
      </Element>
      <Element>
        <Index>2</Index>
        <Position>
          <x>-103.4</x>
          <y>-58.3491</y>
          <z>-669.481</z>
        </Position>
        <Rotation>
          <x>0</x>
          <y>0.732348</y>
          <z>0</z>
          <w>-0.68093</w>
        </Rotation>
      </Element>
      <Element>
        <Index>3</Index>
        <Position>
          <x>-105.395</x>
          <y>-58.3463</y>
          <z>-669.626</z>
        </Position>
        <Rotation>
          <x>0</x>
          <y>0.732348</y>
          <z>0</z>
          <w>-0.68093</w>
        </Rotation>
      </Element>
      <Element>
        <Index>4</Index>
        <Position>
          <x>-107.389</x>
          <y>-58.3476</y>
          <z>-669.772</z>
        </Position>
        <Rotation>
          <x>0</x>
          <y>0.732348</y>
          <z>0</z>
          <w>-0.68093</w>
        </Rotation>
      </Element>
      <BaseLine>1</BaseLine>
      <Direction>0</Direction>
      <Interval>2</Interval>
      <IntervalBase>0</IntervalBase>
      <PositionBase>0</PositionBase>
      <RotationBase>0</RotationBase>
    </MultiSetParam>
  </Ring>
  <EventCollision>
    <Collision_Height>48</Collision_Height>
    <Collision_Length>10</Collision_Length>
    <Collision_Width>43</Collision_Width>
    <DefaultStatus>0</DefaultStatus>
    <Durability>0</Durability>
    <Event0>6</Event0>
    <Event1>0</Event1>
    <Event2>0</Event2>
    <Event3>0</Event3>
    <GroundOffset>0</GroundOffset>
    <Shape_Type>0</Shape_Type>
    <TargetList0>
      <SetObjectID>12369</SetObjectID>
    </TargetList0>
    <TargetList1 />
    <TargetList2 />
    <TargetList3 />
    <Timer0>0</Timer0>
    <Timer1>0</Timer1>
    <Timer2>0</Timer2>
    <Timer3>0</Timer3>
    <Trigger>
      <SetObjectID>0</SetObjectID>
    </Trigger>
    <TriggerType>0</TriggerType>
    <Position>
      <x>189.479</x>
      <y>6.00828</y>
      <z>-40.9291</z>
    </Position>
    <Rotation>
      <x>0</x>
      <y>0.300968</y>
      <z>0</z>
      <w>0.953634</w>
    </Rotation>
    <SetObjectID>12368</SetObjectID>
  </EventCollision>
  <Hint>
    <Category>0</Category>
    <ChangeTime>-0.1</ChangeTime>
    <CharaType>1</CharaType>
    <DrawCharWait>-0.01</DrawCharWait>
    <DrawOnce>true</DrawOnce>
    <EndWait>-0.1</EndWait>
    <ExistPlatform>false</ExistPlatform>
    <GroundOffset>0</GroundOffset>
    <GroupID>WhiteIsland_ACT1_004</GroupID>
    <NeedInput>false</NeedInput>
    <PlayerStop>false</PlayerStop>
    <UsePicture>false</UsePicture>
    <Position>
      <x>142.088</x>
      <y>3.3134</y>
      <z>-89.2511</z>
    </Position>
    <Rotation>
      <x>0</x>
      <y>0</y>
      <z>0</z>
      <w>1</w>
    </Rotation>
    <SetObjectID>12369</SetObjectID>
  </Hint>
  <Spring>
    <DebugShotTimeLength>2</DebugShotTimeLength>
    <FirstSpeed>17</FirstSpeed>
    <GroundOffset>0</GroundOffset>
    <HasBase>true</HasBase>
    <IsChangeCameraWhenPathChange>true</IsChangeCameraWhenPathChange>
    <IsPathChange>false</IsPathChange>
    <IsStartVelocityConstant>true</IsStartVelocityConstant>
    <IsWallWalk>false</IsWallWalk>
    <IsYawUpdate>false</IsYawUpdate>
    <KeepVelocityDistance>5</KeepVelocityDistance>
    <OutOfControl>0.5</OutOfControl>
    <m_IsConstantFrame>false</m_IsConstantFrame>
    <m_IsConstantPosition>true</m_IsConstantPosition>
    <m_IsMonkeyHunting>false</m_IsMonkeyHunting>
    <m_IsMonkeyHuntingLowAngle>true</m_IsMonkeyHuntingLowAngle>
    <m_IsStopBoost>false</m_IsStopBoost>
    <m_IsTo3D>false</m_IsTo3D>
    <m_MonkeyTarget>
      <x>21.0159</x>
      <y>-69.4338</y>
      <z>-623.638</z>
    </m_MonkeyTarget>
    <Range>30</Range>
    <Position>
      <x>19.4923</x>
      <y>-69.4338</y>
      <z>-623.214</z>
    </Position>
    <Rotation>
      <x>0.00872653</x>
      <y>0</y>
      <z>0</z>
      <w>0.999962</w>
    </Rotation>
    <SetObjectID>12370</SetObjectID>
    <MultiSetParam>
      <Element>
        <Index>1</Index>
        <Position>
          <x>20.9923</x>
          <y>-69.4338</y>
          <z>-623.214</z>
        </Position>
        <Rotation>
          <x>0.00872653</x>
          <y>0</y>
          <z>0</z>
          <w>0.999962</w>
        </Rotation>
      </Element>
      <Element>
        <Index>2</Index>
        <Position>
          <x>22.4923</x>
          <y>-69.4338</y>
          <z>-623.214</z>
        </Position>
        <Rotation>
          <x>0.00872653</x>
          <y>0</y>
          <z>0</z>
          <w>0.999962</w>
        </Rotation>
      </Element>
      <BaseLine>0</BaseLine>
      <Direction>1</Direction>
      <Interval>1.5</Interval>
      <IntervalBase>0</IntervalBase>
      <PositionBase>0</PositionBase>
      <RotationBase>0</RotationBase>
    </MultiSetParam>
  </Spring>
  <Hint>
    <Category>0</Category>
    <ChangeTime>-0.1</ChangeTime>
    <CharaType>1</CharaType>
    <DrawCharWait>-0.01</DrawCharWait>
    <DrawOnce>true</DrawOnce>
    <EndWait>-0.1</EndWait>
    <ExistPlatform>false</ExistPlatform>
    <GroundOffset>0</GroundOffset>
    <GroupID>WhiteIsland_ACT1_009</GroupID>
    <NeedInput>false</NeedInput>
    <PlayerStop>false</PlayerStop>
    <UsePicture>false</UsePicture>
    <Position>
      <x>-5.81947</x>
      <y>-63.5375</y>
      <z>-669.344</z>
    </Position>
    <Rotation>
      <x>0</x>
      <y>0</y>
      <z>0</z>
      <w>1</w>
    </Rotation>
    <SetObjectID>12371</SetObjectID>
  </Hint>
  <EventCollision>
    <Collision_Height>6</Collision_Height>
    <Collision_Length>30</Collision_Length>
    <Collision_Width>45</Collision_Width>
    <DefaultStatus>0</DefaultStatus>
    <Durability>0</Durability>
    <Event0>6</Event0>
    <Event1>0</Event1>
    <Event2>0</Event2>
    <Event3>0</Event3>
    <GroundOffset>0</GroundOffset>
    <Shape_Type>0</Shape_Type>
    <TargetList0>
      <SetObjectID>12371</SetObjectID>
    </TargetList0>
    <TargetList1 />
    <TargetList2 />
    <TargetList3 />
    <Timer0>0</Timer0>
    <Timer1>0</Timer1>
    <Timer2>0</Timer2>
    <Timer3>0</Timer3>
    <Trigger>
      <SetObjectID>0</SetObjectID>
    </Trigger>
    <TriggerType>0</TriggerType>
    <Position>
      <x>-21.8413</x>
      <y>-65.9401</y>
      <z>-668.775</z>
    </Position>
    <Rotation>
      <x>0</x>
      <y>0</y>
      <z>0</z>
      <w>1</w>
    </Rotation>
    <SetObjectID>12372</SetObjectID>
  </EventCollision>
</SetObject>
